<annotation>
	<folder>BMT_image</folder>
	<filename>10311370131923821_86로1560.jpg</filename>
	<path>D:\SPB_Data\Mask-RCNN-TF2\car-plate-learning\BMT_image\10311370131923821_86로1560.jpg</path>
	<source>
		<database>Unknown</database>
	</source>
	<size>
		<width>1300</width>
		<height>1024</height>
		<depth>1</depth>
	</size>
	<segmented>0</segmented>
	<object>
		<name>car</name>
		<pose>Unspecified</pose>
		<truncated>0</truncated>
		<difficult>0</difficult>
		<bndbox>
			<xmin>515</xmin>
			<ymin>292</ymin>
			<xmax>1208</xmax>
			<ymax>884</ymax>
		</bndbox>
	</object>
	<object>
		<name>plate</name>
		<pose>Unspecified</pose>
		<truncated>0</truncated>
		<difficult>0</difficult>
		<bndbox>
			<xmin>744</xmin>
			<ymin>738</ymin>
			<xmax>997</xmax>
			<ymax>802</ymax>
		</bndbox>
	</object>
</annotation>
